[
    {
        "ClassName": "M4_Suppressor",
        "DisplayName": "M4 Suppressor",
        "Category": "Sniper_Rifles",
        "DeliveryGroup": "Sniper_Rifles",
        "BuyPrice": 10,
        "SellPrice": 5,
        "CanBuy": true,
        "CanSell": true,
        "DeliveryItem": true,
        "DeliverySize": 1,
        "SpawnAttachments": [],
        "OptionalAttachments": [],
        "Variants": [],
        "IsVariant": false
    },
    {
        "ClassName": "BC_Accupower_Optic",
        "DisplayName": "BC Accupower Optic",
        "Category": "Sniper_Rifles",
        "DeliveryGroup": "Sniper_Rifles",
        "BuyPrice": 10,
        "SellPrice": 5,
        "CanBuy": true,
        "CanSell": true,
        "DeliveryItem": true,
        "DeliverySize": 1,
        "SpawnAttachments": [],
        "OptionalAttachments": [],
        "Variants": [],
        "IsVariant": false
    },
    {
        "ClassName": "BC_ACOG_ACSS_Optic",
        "DisplayName": "BC ACOG ACSS Optic",
        "Category": "Sniper_Rifles",
        "DeliveryGroup": "Sniper_Rifles",
        "BuyPrice": 10,
        "SellPrice": 5,
        "CanBuy": true,
        "CanSell": true,
        "DeliveryItem": true,
        "DeliverySize": 1,
        "SpawnAttachments": [],
        "OptionalAttachments": [],
        "Variants": [],
        "IsVariant": false
    },
    {
        "ClassName": "BC_EoTechVuduOptic",
        "DisplayName": "BC Eo Tech Vudu Optic",
        "Category": "Sniper_Rifles",
        "DeliveryGroup": "Sniper_Rifles",
        "BuyPrice": 10,
        "SellPrice": 5,
        "CanBuy": true,
        "CanSell": true,
        "DeliveryItem": true,
        "DeliverySize": 1,
        "SpawnAttachments": [],
        "OptionalAttachments": [],
        "Variants": [],
        "IsVariant": false
    },
    {
        "ClassName": "BC_HAMROptic",
        "DisplayName": "BC HAMROptic",
        "Category": "Sniper_Rifles",
        "DeliveryGroup": "Sniper_Rifles",
        "BuyPrice": 10,
        "SellPrice": 5,
        "CanBuy": true,
        "CanSell": true,
        "DeliveryItem": true,
        "DeliverySize": 1,
        "SpawnAttachments": [],
        "OptionalAttachments": [],
        "Variants": [],
        "IsVariant": false
    },
    {
        "ClassName": "BC_HolosunHS507C_Optic",
        "DisplayName": "BC Holosun HS507C Optic",
        "Category": "Sniper_Rifles",
        "DeliveryGroup": "Sniper_Rifles",
        "BuyPrice": 10,
        "SellPrice": 5,
        "CanBuy": true,
        "CanSell": true,
        "DeliveryItem": true,
        "DeliverySize": 1,
        "SpawnAttachments": [],
        "OptionalAttachments": [],
        "Variants": [],
        "IsVariant": false
    },
    {
        "ClassName": "BC_LeupoldHoloDEvoOptic",
        "DisplayName": "BC Leupold Holo DEvo Optic",
        "Category": "Sniper_Rifles",
        "DeliveryGroup": "Sniper_Rifles",
        "BuyPrice": 10,
        "SellPrice": 5,
        "CanBuy": true,
        "CanSell": true,
        "DeliveryItem": true,
        "DeliverySize": 1,
        "SpawnAttachments": [],
        "OptionalAttachments": [],
        "Variants": [],
        "IsVariant": false
    },
    {
        "ClassName": "BC_Vortex_RazorHD_Optic",
        "DisplayName": "BC Vortex Razor HD Optic",
        "Category": "Sniper_Rifles",
        "DeliveryGroup": "Sniper_Rifles",
        "BuyPrice": 10,
        "SellPrice": 5,
        "CanBuy": true,
        "CanSell": true,
        "DeliveryItem": true,
        "DeliverySize": 1,
        "SpawnAttachments": [],
        "OptionalAttachments": [],
        "Variants": [],
        "IsVariant": false
    },
    {
        "ClassName": "BC_VortexAMG_UH1_Optic",
        "DisplayName": "BC Vortex AMG UH1 Optic",
        "Category": "Sniper_Rifles",
        "DeliveryGroup": "Sniper_Rifles",
        "BuyPrice": 10,
        "SellPrice": 5,
        "CanBuy": true,
        "CanSell": true,
        "DeliveryItem": true,
        "DeliverySize": 1,
        "SpawnAttachments": [],
        "OptionalAttachments": [],
        "Variants": [],
        "IsVariant": false
    },
    {
        "ClassName": "XM7_Suppressor",
        "DisplayName": "XM7 Suppressor",
        "Category": "Sniper_Rifles",
        "DeliveryGroup": "Sniper_Rifles",
        "BuyPrice": 10,
        "SellPrice": 5,
        "CanBuy": true,
        "CanSell": true,
        "DeliveryItem": true,
        "DeliverySize": 1,
        "SpawnAttachments": [],
        "OptionalAttachments": [],
        "Variants": [],
        "IsVariant": false
    },
    {
        "ClassName": "XM7_Tan",
        "DisplayName": "XM7 Tan",
        "Category": "Sniper_Rifles",
        "DeliveryGroup": "Sniper_Rifles",
        "BuyPrice": 50,
        "SellPrice": 25,
        "CanBuy": true,
        "CanSell": true,
        "DeliveryItem": true,
        "DeliverySize": 1,
        "SpawnAttachments": [],
        "OptionalAttachments": [],
        "Variants": [],
        "IsVariant": false
    },
    {
        "ClassName": "XM7_FDE",
        "DisplayName": "XM7 FDE",
        "Category": "Sniper_Rifles",
        "DeliveryGroup": "Sniper_Rifles",
        "BuyPrice": 50,
        "SellPrice": 25,
        "CanBuy": true,
        "CanSell": true,
        "DeliveryItem": true,
        "DeliverySize": 1,
        "SpawnAttachments": [],
        "OptionalAttachments": [],
        "Variants": [],
        "IsVariant": false
    },
    {
        "ClassName": "XM7_Bttstck",
        "DisplayName": "XM7 Bttstck",
        "Category": "Sniper_Rifles",
        "DeliveryGroup": "Sniper_Rifles",
        "BuyPrice": 50,
        "SellPrice": 25,
        "CanBuy": true,
        "CanSell": true,
        "DeliveryItem": true,
        "DeliverySize": 1,
        "SpawnAttachments": [],
        "OptionalAttachments": [],
        "Variants": [],
        "IsVariant": false
    },
    {
        "ClassName": "XM7_20Rnd_Magazine",
        "DisplayName": "XM7 20Rnd Magazine",
        "Category": "Sniper_Rifles",
        "DeliveryGroup": "Sniper_Rifles",
        "BuyPrice": 10,
        "SellPrice": 5,
        "CanBuy": true,
        "CanSell": true,
        "DeliveryItem": true,
        "DeliverySize": 1,
        "SpawnAttachments": [],
        "OptionalAttachments": [],
        "Variants": [],
        "IsVariant": false
    },
    {
        "ClassName": "R700_Suppressor",
        "DisplayName": "R700 Suppressor",
        "Category": "Sniper_Rifles",
        "DeliveryGroup": "Sniper_Rifles",
        "BuyPrice": 10,
        "SellPrice": 5,
        "CanBuy": true,
        "CanSell": true,
        "DeliveryItem": true,
        "DeliverySize": 1,
        "SpawnAttachments": [],
        "OptionalAttachments": [],
        "Variants": [],
        "IsVariant": false
    },
    {
        "ClassName": "R700_10Rnd",
        "DisplayName": "R700 10Rnd",
        "Category": "Sniper_Rifles",
        "DeliveryGroup": "Sniper_Rifles",
        "BuyPrice": 10,
        "SellPrice": 5,
        "CanBuy": true,
        "CanSell": true,
        "DeliveryItem": true,
        "DeliverySize": 1,
        "SpawnAttachments": [],
        "OptionalAttachments": [],
        "Variants": [],
        "IsVariant": false
    },
    {
        "ClassName": "R700",
        "DisplayName": "R700",
        "Category": "Sniper_Rifles",
        "DeliveryGroup": "Sniper_Rifles",
        "BuyPrice": 50,
        "SellPrice": 25,
        "CanBuy": true,
        "CanSell": true,
        "DeliveryItem": true,
        "DeliverySize": 1,
        "SpawnAttachments": [],
        "OptionalAttachments": [],
        "Variants": [],
        "IsVariant": false
    },
    {
        "ClassName": "M98B_5Rnd",
        "DisplayName": "M98B 5Rnd",
        "Category": "Sniper_Rifles",
        "DeliveryGroup": "Sniper_Rifles",
        "BuyPrice": 10,
        "SellPrice": 5,
        "CanBuy": true,
        "CanSell": true,
        "DeliveryItem": true,
        "DeliverySize": 1,
        "SpawnAttachments": [],
        "OptionalAttachments": [],
        "Variants": [],
        "IsVariant": false
    },
    {
        "ClassName": "M98B",
        "DisplayName": "M98B",
        "Category": "Sniper_Rifles",
        "DeliveryGroup": "Sniper_Rifles",
        "BuyPrice": 50,
        "SellPrice": 25,
        "CanBuy": true,
        "CanSell": true,
        "DeliveryItem": true,
        "DeliverySize": 1,
        "SpawnAttachments": [],
        "OptionalAttachments": [],
        "Variants": [],
        "IsVariant": false
    },
    {
        "ClassName": "AWM_5Rnd",
        "DisplayName": "AWM 5Rnd",
        "Category": "Sniper_Rifles",
        "DeliveryGroup": "Sniper_Rifles",
        "BuyPrice": 10,
        "SellPrice": 5,
        "CanBuy": true,
        "CanSell": true,
        "DeliveryItem": true,
        "DeliverySize": 1,
        "SpawnAttachments": [],
        "OptionalAttachments": [],
        "Variants": [],
        "IsVariant": false
    },
    {
        "ClassName": "AWM",
        "DisplayName": "AWM",
        "Category": "Sniper_Rifles",
        "DeliveryGroup": "Sniper_Rifles",
        "BuyPrice": 50,
        "SellPrice": 25,
        "CanBuy": true,
        "CanSell": true,
        "DeliveryItem": true,
        "DeliverySize": 1,
        "SpawnAttachments": [],
        "OptionalAttachments": [],
        "Variants": [],
        "IsVariant": false
    },
    {
        "ClassName": "A2AS50",
        "DisplayName": "A2AS50",
        "Category": "Sniper_Rifles",
        "DeliveryGroup": "Sniper_Rifles",
        "BuyPrice": 50,
        "SellPrice": 25,
        "CanBuy": true,
        "CanSell": true,
        "DeliveryItem": true,
        "DeliverySize": 1,
        "SpawnAttachments": [],
        "OptionalAttachments": [],
        "Variants": [],
        "IsVariant": false
    },
    {
        "ClassName": "A2AS50_Magazine",
        "DisplayName": "A2AS50 Magazine",
        "Category": "Sniper_Rifles",
        "DeliveryGroup": "Sniper_Rifles",
        "BuyPrice": 10,
        "SellPrice": 5,
        "CanBuy": true,
        "CanSell": true,
        "DeliveryItem": true,
        "DeliverySize": 1,
        "SpawnAttachments": [],
        "OptionalAttachments": [],
        "Variants": [],
        "IsVariant": false
    },
    {
        "ClassName": "A2KSVK",
        "DisplayName": "A2KSVK",
        "Category": "Sniper_Rifles",
        "DeliveryGroup": "Sniper_Rifles",
        "BuyPrice": 50,
        "SellPrice": 25,
        "CanBuy": true,
        "CanSell": true,
        "DeliveryItem": true,
        "DeliverySize": 1,
        "SpawnAttachments": [],
        "OptionalAttachments": [],
        "Variants": [],
        "IsVariant": false
    },
    {
        "ClassName": "A2KSVK_Magazine",
        "DisplayName": "A2KSVK Magazine",
        "Category": "Sniper_Rifles",
        "DeliveryGroup": "Sniper_Rifles",
        "BuyPrice": 10,
        "SellPrice": 5,
        "CanBuy": true,
        "CanSell": true,
        "DeliveryItem": true,
        "DeliverySize": 1,
        "SpawnAttachments": [],
        "OptionalAttachments": [],
        "Variants": [],
        "IsVariant": false
    },
    {
        "ClassName": "A2M107",
        "DisplayName": "A2M107",
        "Category": "Sniper_Rifles",
        "DeliveryGroup": "Sniper_Rifles",
        "BuyPrice": 50,
        "SellPrice": 25,
        "CanBuy": true,
        "CanSell": true,
        "DeliveryItem": true,
        "DeliverySize": 1,
        "SpawnAttachments": [],
        "OptionalAttachments": [],
        "Variants": [],
        "IsVariant": false
    },
    {
        "ClassName": "A2M107_Magazine",
        "DisplayName": "A2M107 Magazine",
        "Category": "Sniper_Rifles",
        "DeliveryGroup": "Sniper_Rifles",
        "BuyPrice": 10,
        "SellPrice": 5,
        "CanBuy": true,
        "CanSell": true,
        "DeliveryItem": true,
        "DeliverySize": 1,
        "SpawnAttachments": [],
        "OptionalAttachments": [],
        "Variants": [],
        "IsVariant": false
    },
    {
        "ClassName": "A2M40A3",
        "DisplayName": "A2M40A3",
        "Category": "Sniper_Rifles",
        "DeliveryGroup": "Sniper_Rifles",
        "BuyPrice": 50,
        "SellPrice": 25,
        "CanBuy": true,
        "CanSell": true,
        "DeliveryItem": true,
        "DeliverySize": 1,
        "SpawnAttachments": [],
        "OptionalAttachments": [],
        "Variants": [],
        "IsVariant": false
    },
    {
        "ClassName": "A2M40A3_Magazine",
        "DisplayName": "A2M40A3 Magazine",
        "Category": "Sniper_Rifles",
        "DeliveryGroup": "Sniper_Rifles",
        "BuyPrice": 10,
        "SellPrice": 5,
        "CanBuy": true,
        "CanSell": true,
        "DeliveryItem": true,
        "DeliverySize": 1,
        "SpawnAttachments": [],
        "OptionalAttachments": [],
        "Variants": [],
        "IsVariant": false
    },
    {
        "ClassName": "A2Suppressor",
        "DisplayName": "A2Suppressor",
        "Category": "Sniper_Rifles",
        "DeliveryGroup": "Sniper_Rifles",
        "BuyPrice": 10,
        "SellPrice": 5,
        "CanBuy": true,
        "CanSell": true,
        "DeliveryItem": true,
        "DeliverySize": 1,
        "SpawnAttachments": [],
        "OptionalAttachments": [],
        "Variants": [],
        "IsVariant": false
    },
    {
        "ClassName": "HuntingOptic",
        "DisplayName": "Hunting Optic",
        "Category": "Sniper_Rifles",
        "DeliveryGroup": "Sniper_Rifles",
        "BuyPrice": 10,
        "SellPrice": 5,
        "CanBuy": true,
        "CanSell": true,
        "DeliveryItem": true,
        "DeliverySize": 1,
        "SpawnAttachments": [],
        "OptionalAttachments": [],
        "Variants": [],
        "IsVariant": false
    },
    {
        "ClassName": "ExpansionDeltapointOptic",
        "DisplayName": "Expansion Deltapoint Optic",
        "Category": "Sniper_Rifles",
        "DeliveryGroup": "Sniper_Rifles",
        "BuyPrice": 10,
        "SellPrice": 5,
        "CanBuy": true,
        "CanSell": true,
        "DeliveryItem": true,
        "DeliverySize": 1,
        "SpawnAttachments": [],
        "OptionalAttachments": [],
        "Variants": [],
        "IsVariant": false
    },
    {
        "ClassName": "ExpansionEXPS3HoloOptic",
        "DisplayName": "Expansion EXPS3Holo Optic",
        "Category": "Sniper_Rifles",
        "DeliveryGroup": "Sniper_Rifles",
        "BuyPrice": 10,
        "SellPrice": 5,
        "CanBuy": true,
        "CanSell": true,
        "DeliveryItem": true,
        "DeliverySize": 1,
        "SpawnAttachments": [],
        "OptionalAttachments": [],
        "Variants": [],
        "IsVariant": false
    },
    {
        "ClassName": "ExpansionHAMROptic",
        "DisplayName": "Expansion HAMROptic",
        "Category": "Sniper_Rifles",
        "DeliveryGroup": "Sniper_Rifles",
        "BuyPrice": 10,
        "SellPrice": 5,
        "CanBuy": true,
        "CanSell": true,
        "DeliveryItem": true,
        "DeliverySize": 1,
        "SpawnAttachments": [],
        "OptionalAttachments": [],
        "Variants": [],
        "IsVariant": false
    }
]
